auto_related/__init__.py
auto_related/method_field.py
auto_related/mixin.py
auto_related/tracer.py
auto_related/utils.py
auto_related-0.0.4.dist-info/LICENSE
auto_related-0.0.4.dist-info/METADATA
auto_related-0.0.4.dist-info/WHEEL
auto_related-0.0.4.dist-info/top_level.txt
auto_related-0.0.4.dist-info/RECORD
