Metadata-Version: 2.1
Name: auto-related
Version: 0.0.4
Summary: Optimize serializers automatically with select_related(), prefetch_related(), defer() and only()
Home-page: https://github.com/thetarby/django-auto-related
Author: Furkan Akyol
Author-email: furkanakyol1997@gmail.com
License: MIT
Keywords: django,djangorest,related,select,prefetch,defer,only
Platform: UNKNOWN
Classifier: Development Status :: 4 - Beta
Classifier: Intended Audience :: Developers
Classifier: Topic :: Software Development :: Build Tools
Classifier: License :: OSI Approved :: MIT License
Classifier: Programming Language :: Python :: 3
Classifier: Programming Language :: Python :: 3.4
Classifier: Programming Language :: Python :: 3.5
Classifier: Programming Language :: Python :: 3.6
Classifier: Programming Language :: Python :: 3.7
Classifier: Programming Language :: Python :: 3.8
Requires-Dist: djangorestframework
Requires-Dist: django
